mctech_cloud/metrics/__init__.py
mctech_cloud/metrics/rpc_client_indicator.py
mctech_cloud/middlewares/__init__.py
mctech_cloud/middlewares/metrics_middleware.py
mctech_cloud/middlewares/service_context_middleware.py
mctech_cloud-1.1.0.dist-info/METADATA
mctech_cloud-1.1.0.dist-info/WHEEL
mctech_cloud-1.1.0.dist-info/top_level.txt
mctech_cloud-1.1.0.dist-info/RECORD
