Metadata-Version: 2.1
Name: mctech-cloud
Version: 1.1.0
Summary: UNKNOWN
Home-page: UNKNOWN
License: UNKNOWN
Platform: UNKNOWN
Requires-Dist: log4py
Requires-Dist: fastapi
Requires-Dist: starlette
Requires-Dist: mctech-actuator
Requires-Dist: mctech-discovery
